centrodip/__init__.py
centrodip/bedmethyl_smooth.py
centrodip/bedtable.py
centrodip/detect_dips.py
centrodip/filter_dips.py
centrodip/main.py
centrodip/summary_plot.py
centrodip-1.0.0.dist-info/licenses/LICENSE
centrodip-1.0.0.dist-info/METADATA
centrodip-1.0.0.dist-info/WHEEL
centrodip-1.0.0.dist-info/entry_points.txt
centrodip-1.0.0.dist-info/top_level.txt
centrodip-1.0.0.dist-info/RECORD
