Metadata-Version: 2.4
Name: centrodip
Version: 1.0.0
Summary: Find hypomethylated regions in centromeres
Home-page: https://github.com/jmenendez98/centrodip
Author: Julian Menendez
Author-email: jmmenend@ucsc.edu
License: MIT
Project-URL: GitHub, https://github.com/jmenendez98/centrodip
Project-URL: Lab Website, https://migalab.com/
Classifier: Programming Language :: Python :: 3
Classifier: License :: OSI Approved :: MIT License
Classifier: Operating System :: OS Independent
Requires-Python: >=3.8
License-File: LICENSE
Requires-Dist: numpy>=1.21.5
Requires-Dist: scipy>=1.7.3
Requires-Dist: matplotlib>=3.5.1
Provides-Extra: dev
Requires-Dist: pytest; extra == "dev"
Dynamic: author
Dynamic: author-email
Dynamic: classifier
Dynamic: description
Dynamic: description-content-type
Dynamic: home-page
Dynamic: license
Dynamic: license-file
Dynamic: project-url
Dynamic: provides-extra
Dynamic: requires-dist
Dynamic: requires-python
Dynamic: summary
